pythonloc/__init__.py
pythonloc/__main__.py
pythonloc/pythonloc.py
pythonloc-0.1.2.2.dist-info/LICENSE
pythonloc-0.1.2.2.dist-info/METADATA
pythonloc-0.1.2.2.dist-info/WHEEL
pythonloc-0.1.2.2.dist-info/entry_points.txt
pythonloc-0.1.2.2.dist-info/top_level.txt
pythonloc-0.1.2.2.dist-info/RECORD
