Metadata-Version: 2.1
Name: pythonloc
Version: 0.1.2.2
Summary: Run Python using packages from local directory __pypackages__
Home-page: https://github.com/cs01/pythonloc
Author: Chad Smith
Author-email: chadsmith.software@gmail.com
License: License :: OSI Approved :: MIT License
Platform: UNKNOWN
Classifier: Operating System :: OS Independent
Classifier: License :: OSI Approved :: MIT License
Classifier: Programming Language :: Python
Classifier: Programming Language :: Python :: 2.7
Classifier: Programming Language :: Python :: 3.6
Classifier: Programming Language :: Python :: 3.7
Classifier: Programming Language :: Python :: 3.8
Requires-Python: >=2.7
License-File: LICENSE
Requires-Dist: pipx (>=0.12.2.0) ; python_version >= "3.6"
